VoigtFit/VERSION
VoigtFit/__init__.py
VoigtFit/__main__.py
VoigtFit/main.py
VoigtFit/container/__init__.py
VoigtFit/container/components.py
VoigtFit/container/dataset.py
VoigtFit/container/lines.py
VoigtFit/container/regions.py
VoigtFit/funcs/__init__.py
VoigtFit/funcs/limits.py
VoigtFit/funcs/voigt.py
VoigtFit/io/__init__.py
VoigtFit/io/fits_input.py
VoigtFit/io/hdf5_save.py
VoigtFit/io/output.py
VoigtFit/io/parse_input.py
VoigtFit/static/Asplund2009.dat
VoigtFit/static/Asplund2021.dat
VoigtFit/static/C_complexes.dat
VoigtFit/static/C_full_labels.txt
VoigtFit/static/Konstantopoulou2022.dat
VoigtFit/static/Lodders2009.dat
VoigtFit/static/input_template.txt
VoigtFit/static/linelist.dat
VoigtFit/static/telluric_em_abs.npz
VoigtFit/utils/Asplund.py
VoigtFit/utils/__init__.py
VoigtFit/utils/depletion.py
VoigtFit/utils/line_complexes.py
VoigtFit/utils/molecules.py
VoigtFit/utils/terminal_attributes.py
voigtfit-3.22.dist-info/licenses/LICENSE
voigtfit-3.22.dist-info/METADATA
voigtfit-3.22.dist-info/WHEEL
voigtfit-3.22.dist-info/entry_points.txt
voigtfit-3.22.dist-info/top_level.txt
voigtfit-3.22.dist-info/RECORD
