Metadata-Version: 2.4
Name: VoigtFit
Version: 3.22
Summary: Voigt Profile Fitting in Python
Author-email: Jens-Kristian Krogager <jens-kristian.krogager@univ-lyon1.fr>
License-Expression: MIT
Keywords: voigtfit,absorption,analysis,voigt,spectroscopy,fitting
Classifier: Programming Language :: Python :: 3
Requires-Python: >=3.8
License-File: LICENSE
Requires-Dist: astropy
Requires-Dist: future
Requires-Dist: h5py>=2.1
Requires-Dist: lmfit
Requires-Dist: matplotlib
Requires-Dist: numpy
Requires-Dist: scipy
Dynamic: license-file
